{
    "dto":{
        "hostName":"DB",
        "hostIp":"172.31.3.2",
        "totalCpu":16,
        "totalMemory":32000,
        "totalDisk":300,
        "pooledDisk":300,
        "hostType":"Master",
        "hypervisorType":"LXC",
        "cpuArch":"x86_64",
        "availabilityZone":"",
        "status":"Running",
        "hostPmac":"fe:a7:c1:06",
        "frontendPort":"eno1.2",
        "backendPort":"eno1.3",
        "managementPort":"eno1",
        "switchDpid":2038033768499423169,
        "switchPort":6,
        "accessName":"root",
        "accessAuth":"tmax@23",
        "active":true
    }
}
